iregexp_check-0.1.4.dist-info/METADATA
iregexp_check-0.1.4.dist-info/WHEEL
iregexp_check/__init__.py
iregexp_check/__init__.pyi
iregexp_check/py.typed
iregexp_check/iregexp_check.abi3.so
iregexp_check-0.1.4.dist-info/RECORD
