Metadata-Version: 2.3
Name: iregexp-check
Version: 0.1.4
Classifier: Development Status :: 4 - Beta
Classifier: Intended Audience :: Developers
Classifier: License :: OSI Approved :: MIT License
Classifier: Programming Language :: Rust
Classifier: Programming Language :: Python :: Implementation :: CPython
Classifier: Programming Language :: Python :: Implementation :: PyPy
Classifier: Programming Language :: Python :: 3.8
Classifier: Programming Language :: Python :: 3.9
Classifier: Programming Language :: Python :: 3.10
Classifier: Programming Language :: Python :: 3.11
Classifier: Programming Language :: Python :: 3.12
Classifier: Programming Language :: Python :: 3.13
Author-email: James Prior <jamesgr.prior@gmail.com>
Requires-Python: >=3.8
Project-URL: Change Log, https://github.com/jg-rp/rust-iregexp/blob/main/CHANGES.md
Project-URL: Homepage, https://github.com/jg-rp/rust-iregexp/tree/main/crates/python
Project-URL: Issue Tracker, https://github.com/jg-rp/rust-iregexp/issues
Project-URL: Source Code, https://github.com/jg-rp/rust-iregexp/tree/main/crates/python
